autorace_tokyo_sports_scraper-0.1.9.dist-info/licenses/LICENSE
tests/test_builder.py
tokyo_sports_scraper/__init__.py
tokyo_sports_scraper/builder.py
tokyo_sports_scraper/formatter.py
tokyo_sports_scraper/model.py
tokyo_sports_scraper/scraper.py
tokyo_sports_scraper/extractors/__init__.py
tokyo_sports_scraper/extractors/race_info.py
tokyo_sports_scraper/extractors/rider_info.py
tokyo_sports_scraper/extractors/utils.py
autorace_tokyo_sports_scraper-0.1.9.dist-info/METADATA
autorace_tokyo_sports_scraper-0.1.9.dist-info/WHEEL
autorace_tokyo_sports_scraper-0.1.9.dist-info/top_level.txt
autorace_tokyo_sports_scraper-0.1.9.dist-info/RECORD
